kross/__init__.py
kross/archs.yaml
kross/base_build.py
kross/base_push.py
kross/builder.py
kross/main.py
kross/qemu_build.py
kross/qemu_push.py
kross/utils.py
kross/qemu/x86_64_qemu-aarch64-static.tar.gz
kross/qemu/x86_64_qemu-arm-static.tar.gz
kross/qemu/x86_64_qemu-i386-static.tar.gz
kross/qemu/x86_64_qemu-ppc64le-static.tar.gz
kross/qemu/x86_64_qemu-s390x-static.tar.gz
kross/qemu/x86_64_qemu-x86_64-static.tar.gz
kross-1.0.4.dist-info/LICENSE
kross-1.0.4.dist-info/METADATA
kross-1.0.4.dist-info/WHEEL
kross-1.0.4.dist-info/entry_points.txt
kross-1.0.4.dist-info/top_level.txt
kross-1.0.4.dist-info/RECORD
