Metadata-Version: 2.1
Name: kross
Version: 1.0.4
Summary: A simple CLI to "multi-arch all the things"
Home-page: https://github.com/pcorbel/kross
Author: pcorbel
Author-email: pierrot.corbel@gmail.com
License: apache-2.0
Download-URL: https://github.com/pcorbel/kross/archive/v1.0.4.tar.gz
Platform: UNKNOWN
Classifier: Intended Audience :: Developers
Classifier: License :: OSI Approved :: Apache Software License
Classifier: Programming Language :: Python
Classifier: Programming Language :: Python :: 2
Classifier: Programming Language :: Python :: 2.7
Classifier: Programming Language :: Python :: 3
Classifier: Programming Language :: Python :: 3.5
Classifier: Programming Language :: Python :: 3.6
Classifier: Programming Language :: Python :: 3.7
Classifier: Topic :: Software Development :: Build Tools
Classifier: Topic :: Utilities
